genki_widgets/__init__.py
genki_widgets/_frontend.py
genki_widgets/_version.py
genki_widgets/bar.py
genki_widgets/baseplot.py
genki_widgets/dashboard.py
genki_widgets/line.py
genki_widgets/spectrogram.py
genki_widgets/trace.py
genki_widgets/labextension/build_log.json
genki_widgets/labextension/package.json
genki_widgets/labextension/static/lib_bar_js-lib_dashboard_js-lib_line_js-lib_spectrogram_js-lib_trace_js.8a25edd24886d9e09bba.js
genki_widgets/labextension/static/lib_bar_js-lib_dashboard_js-lib_line_js-lib_spectrogram_js-lib_trace_js.8a25edd24886d9e09bba.js.map
genki_widgets/labextension/static/lib_index_js.a46deb220b361504f716.js
genki_widgets/labextension/static/lib_index_js.a46deb220b361504f716.js.map
genki_widgets/labextension/static/lib_plugin_js.69376c520fde14c52b4c.js
genki_widgets/labextension/static/lib_plugin_js.69376c520fde14c52b4c.js.map
genki_widgets/labextension/static/remoteEntry.1cbd479e7498c5484caa.js
genki_widgets/labextension/static/remoteEntry.1cbd479e7498c5484caa.js.map
genki_widgets/labextension/static/style.js
genki_widgets/labextension/static/vendors-node_modules_scichart_Charting_Visuals_Annotations_AnnotationBase_js-node_modules_sci-af5599.2d14da904ac045b32b97.js
genki_widgets/labextension/static/vendors-node_modules_scichart_Charting_Visuals_Annotations_AnnotationBase_js-node_modules_sci-af5599.2d14da904ac045b32b97.js.map
genki_widgets/labextension/static/vendors-node_modules_scichart_index_js.5b27814b6d867904fc8c.js
genki_widgets/labextension/static/vendors-node_modules_scichart_index_js.5b27814b6d867904fc8c.js.map
genki_widgets/nbextension/extension.js
genki_widgets/nbextension/index.js
genki_widgets/nbextension/index.js.map
genki_widgets/tests/__init__.py
genki_widgets/tests/conftest.py
genki_widgets/tests/test_example.py
genki_widgets/tests/test_nbextension_path.py
genki_widgets-0.1.0.dev0.data/data/share/jupyter/labextensions/genki_widgets/build_log.json
genki_widgets-0.1.0.dev0.dist-info/METADATA
genki_widgets-0.1.0.dev0.dist-info/WHEEL
genki_widgets-0.1.0.dev0.dist-info/licenses/LICENSE.txt
genki_widgets-0.1.0.dev0.dist-info/RECORD
